pincell_moment_utils/__init__.py
pincell_moment_utils/config.py
pincell_moment_utils/data/cas14.h5
pincell_moment_utils/data/cas25.h5
pincell_moment_utils/data/cas70.h5
pincell_moment_utils/data/cas8.h5
pincell_moment_utils/datagen.py
pincell_moment_utils/input_files/pincell.py
pincell_moment_utils/plotting.py
pincell_moment_utils/postprocessing.py
pincell_moment_utils/sampling.py
pincell_moment_utils-0.0.4.dist-info/LICENSE
pincell_moment_utils-0.0.4.dist-info/METADATA
pincell_moment_utils-0.0.4.dist-info/WHEEL
pincell_moment_utils-0.0.4.dist-info/RECORD
