Metadata-Version: 2.3
Name: pincell_moment_utils
Version: 0.0.4
Summary: A tool for postprocessing and calculating flux moments for a pincell model
License: MIT
Author: Matthew Louis
Author-email: matthewlouis31@gmail.com
Requires-Python: >=3.8,<4.0
Classifier: License :: OSI Approved :: MIT License
Classifier: Programming Language :: Python :: 3
Classifier: Programming Language :: Python :: 3.8
Classifier: Programming Language :: Python :: 3.9
Classifier: Programming Language :: Python :: 3.10
Classifier: Programming Language :: Python :: 3.11
Classifier: Programming Language :: Python :: 3.12
Classifier: Programming Language :: Python :: 3.13
Requires-Dist: emcee
Requires-Dist: matplotlib
Requires-Dist: mpi4py
Requires-Dist: numpy
Requires-Dist: openmc
Requires-Dist: pandas
Requires-Dist: py7zr
Requires-Dist: pyprojroot
Requires-Dist: scipy
Requires-Dist: tqdm
Requires-Dist: typing
Requires-Dist: zarr
Project-URL: Documentation, https://mlouis9.github.io/pincell_moment_utils
Project-URL: Homepage, https://github.com/mlouis9/pincell_moment_utils
Project-URL: Issues, https://github.com/mlouis9/pincell_moment_utils/issues
